vam/whittaker/__init__.py
vam/whittaker/_whit.cp39-win_amd64.pyd
vam/whittaker/_whittaker.c
vam/whittaker/_whittaker.pyx
vam/whittaker/_version/__init__.py
vam.whittaker-2.0.6.dist-info/LICENSE
vam.whittaker-2.0.6.dist-info/METADATA
vam.whittaker-2.0.6.dist-info/WHEEL
vam.whittaker-2.0.6.dist-info/top_level.txt
vam.whittaker-2.0.6.dist-info/RECORD
